todus3/__init__.py
todus3/__main__.py
todus3/client.py
todus3/errors.py
todus3/main.py
todus3/s3.py
todus3/util.py
todus3-0.9.0.dist-info/entry_points.txt
todus3-0.9.0.dist-info/LICENSE
todus3-0.9.0.dist-info/WHEEL
todus3-0.9.0.dist-info/METADATA
todus3-0.9.0.dist-info/RECORD
